{"Poster_Link": "https://m.media-amazon.com/images/M/MV5BYTdhNjBjZDctYTlkYy00ZGIxLWFjYTktODk5ZjNlMzI4NjI3XkEyXkFqcGdeQXVyMjY1MjkzMjE@._V1_UY98_CR0,0,67,98_AL_.jpg", "Series_Title": "Baby", "Released_Year": "2015", "Certificate": "UA", "Runtime": "159 min", "Genre": "Action, Crime, Thriller", "IMDB_Rating": 8.0, "Overview": "An elite counter-intelligence unit learns of a plot, masterminded by a maniacal madman. With the clock ticking, it's up to them to track the terrorists' international tentacles and prevent them from striking at the heart of India.", "Meta_score": NaN, "Director": "Neeraj Pandey", "Star1": "Akshay Kumar", "Star2": "Danny Denzongpa", "Star3": "Rana Daggubati", "Star4": "Taapsee Pannu", "No_of_Votes": 52848, "Gross": NaN}