{"Poster_Link": "https://m.media-amazon.com/images/M/MV5BMGUyM2ZiZmUtMWY0OC00NTQ4LThkOGUtNjY2NjkzMDJiMWMwXkEyXkFqcGdeQXVyMzY0MTE3NzU@._V1_UX67_CR0,0,67,98_AL_.jpg", "Series_Title": "The Irishman", "Released_Year": "2019", "Certificate": "R", "Runtime": "209 min", "Genre": "Biography, Crime, Drama", "IMDB_Rating": 7.9, "Overview": "An old man recalls his time painting houses for his friend, Jimmy Hoffa, through the 1950-70s.", "Meta_score": 94.0, "Director": "Martin Scorsese", "Star1": "Robert De Niro", "Star2": "Al Pacino", "Star3": "Joe Pesci", "Star4": "Harvey Keitel", "No_of_Votes": 324720, "Gross": "7,000,000"}