{"Poster_Link": "https://m.media-amazon.com/images/M/MV5BMjc4MTUxN2UtMmU1NC00MjQyLTk3YTYtZTQ0YzEzZDc0Njc0XkEyXkFqcGdeQXVyNjU0OTQ0OTY@._V1_UX67_CR0,0,67,98_AL_.jpg", "Series_Title": "Spartacus", "Released_Year": "1960", "Certificate": "A", "Runtime": "197 min", "Genre": "Adventure, Biography, Drama", "IMDB_Rating": 7.9, "Overview": "The slave Spartacus leads a violent revolt against the decadent Roman Republic.", "Meta_score": 87.0, "Director": "Stanley Kubrick", "Star1": "Kirk Douglas", "Star2": "Laurence Olivier", "Star3": "Jean Simmons", "Star4": "Charles Laughton", "No_of_Votes": 124339, "Gross": "30,000,000"}