{"Poster_Link": "https://m.media-amazon.com/images/M/MV5BZjc4NDZhZWMtNGEzYS00ZWU2LThlM2ItNTA0YzQ0OTExMTE2XkEyXkFqcGdeQXVyNjUwMzI2NzU@._V1_UY98_CR0,0,67,98_AL_.jpg", "Series_Title": "It's a Wonderful Life", "Released_Year": "1946", "Certificate": "PG", "Runtime": "130 min", "Genre": "Drama, Family, Fantasy", "IMDB_Rating": 8.6, "Overview": "An angel is sent from Heaven to help a desperately frustrated businessman by showing him what life would have been like if he had never existed.", "Meta_score": 89.0, "Director": "Frank Capra", "Star1": "James Stewart", "Star2": "Donna Reed", "Star3": "Lionel Barrymore", "Star4": "Thomas Mitchell", "No_of_Votes": 405801, "Gross": NaN}