{"Poster_Link": "https://m.media-amazon.com/images/M/MV5BMjg4ZmY1MmItMjFjOS00ZTg2LWJjNDYtNDM2YmM2NzhiNmZhXkEyXkFqcGdeQXVyNTAzMTY4MDA@._V1_UX67_CR0,0,67,98_AL_.jpg", "Series_Title": "The Florida Project", "Released_Year": "2017", "Certificate": "A", "Runtime": "111 min", "Genre": "Drama", "IMDB_Rating": 7.6, "Overview": "Set over one summer, the film follows precocious six-year-old Moonee as she courts mischief and adventure with her ragtag playmates and bonds with her rebellious but caring mother, all while living in the shadows of Walt Disney World.", "Meta_score": 92.0, "Director": "Sean Baker", "Star1": "Brooklynn Prince", "Star2": "Bria Vinaite", "Star3": "Willem Dafoe", "Star4": "Christopher Rivera", "No_of_Votes": 95181, "Gross": "5,904,366"}