{"Poster_Link": "https://m.media-amazon.com/images/M/MV5BNGQyNjBjNTUtNTM1OS00YzcyLWFhNTgtNTU0MDg3NzBlMDQzXkEyXkFqcGdeQXVyNjc1NTYyMjg@._V1_UY98_CR0,0,67,98_AL_.jpg", "Series_Title": "The Innocents", "Released_Year": "1961", "Certificate": "A", "Runtime": "100 min", "Genre": "Horror", "IMDB_Rating": 7.8, "Overview": "A young governess for two children becomes convinced that the house and grounds are haunted.", "Meta_score": 88.0, "Director": "Jack Clayton", "Star1": "Deborah Kerr", "Star2": "Peter Wyngarde", "Star3": "Megs Jenkins", "Star4": "Michael Redgrave", "No_of_Votes": 27007, "Gross": "2,616,000"}