{"Poster_Link": "https://m.media-amazon.com/images/M/MV5BYjZjODRlMjQtMjJlYy00ZDBjLTkyYTQtZGQxZTk5NzJhYmNmXkEyXkFqcGdeQXVyMTQxNzMzNDI@._V1_UY98_CR1,0,67,98_AL_.jpg", "Series_Title": "Fa yeung nin wah", "Released_Year": "2000", "Certificate": "U", "Runtime": "98 min", "Genre": "Drama, Romance", "IMDB_Rating": 8.1, "Overview": "Two neighbors, a woman and a man, form a strong bond after both suspect extramarital activities of their spouses. However, they agree to keep their bond platonic so as not to commit similar wrongs.", "Meta_score": 85.0, "Director": "Kar-Wai Wong", "Star1": "Tony Chiu-Wai Leung", "Star2": "Maggie Cheung", "Star3": "Ping Lam Siu", "Star4": "Tung Cho 'Joe' Cheung", "No_of_Votes": 124383, "Gross": "2,734,044"}