{"Poster_Link": "https://m.media-amazon.com/images/M/MV5BMGUwZjliMTAtNzAxZi00MWNiLWE2NzgtZGUxMGQxZjhhNDRiXkEyXkFqcGdeQXVyNjU1NzU3MzE@._V1_UX67_CR0,0,67,98_AL_.jpg", "Series_Title": "Knives Out", "Released_Year": "2019", "Certificate": "UA", "Runtime": "130 min", "Genre": "Comedy, Crime, Drama", "IMDB_Rating": 7.9, "Overview": "A detective investigates the death of a patriarch of an eccentric, combative family.", "Meta_score": 82.0, "Director": "Rian Johnson", "Star1": "Daniel Craig", "Star2": "Chris Evans", "Star3": "Ana de Armas", "Star4": "Jamie Lee Curtis", "No_of_Votes": 454203, "Gross": "165,359,751"}