{"Poster_Link": "https://m.media-amazon.com/images/M/MV5BYmUxY2MyOTQtYjRlMi00ZWEwLTkzODctZDMxNDcyNTFhYjNjXkEyXkFqcGdeQXVyNDk3NzU2MTQ@._V1_UY98_CR1,0,67,98_AL_.jpg", "Series_Title": "Being John Malkovich", "Released_Year": "1999", "Certificate": "R", "Runtime": "113 min", "Genre": "Comedy, Drama, Fantasy", "IMDB_Rating": 7.7, "Overview": "A puppeteer discovers a portal that leads literally into the head of movie star John Malkovich.", "Meta_score": 90.0, "Director": "Spike Jonze", "Star1": "John Cusack", "Star2": "Cameron Diaz", "Star3": "Catherine Keener", "Star4": "John Malkovich", "No_of_Votes": 312542, "Gross": "22,858,926"}