{"Poster_Link": "https://m.media-amazon.com/images/M/MV5BOGY1YmUzN2MtNDQ3NC00Nzc4LWI5M2EtYzUwMGQ4NWM4NjE1XkEyXkFqcGdeQXVyMTQxNzMzNDI@._V1_UY98_CR0,0,67,98_AL_.jpg", "Series_Title": "In America", "Released_Year": "2002", "Certificate": "PG-13", "Runtime": "105 min", "Genre": "Drama", "IMDB_Rating": 7.7, "Overview": "A family of Irish immigrants adjust to life on the mean streets of Hell's Kitchen while also grieving the death of a child.", "Meta_score": 76.0, "Director": "Jim Sheridan", "Star1": "Paddy Considine", "Star2": "Samantha Morton", "Star3": "Djimon Hounsou", "Star4": "Sarah Bolger", "No_of_Votes": 40403, "Gross": "15,539,266"}